{
  "marca": {
    "id": "infiniti",
    "nombre": "INFINITI",
    "slug": "infiniti",
    "activa": true,
    "popular": false
  },
  "modelos": [
    {
      "id": "q50",
      "nombre": "Q50",
      "slug": "q50",
      "años": [2014, 2015, 2016, 2017, 2018, 2019, 2020, 2021, 2022, 2023, 2024],
      "generaciones": [
        {
          "nombre": "Primera Generación (2014-presente)",
          "años": [2014, 2015, 2016, 2017, 2018, 2019, 2020, 2021, 2022, 2023, 2024],
          "caracteristicas": ["Motor 2.0L Turbo/3.0L V6 Turbo/3.7L V6", "Transmisión automática 7 velocidades", "Tracción trasera/AWD", "Sedán deportivo de lujo"]
        }
      ],
      "categorias": ["calefaccion-aire-acondicionado", "carroceria-ensamblaje-lampara", "combustible-aire", "correa-transmision", "direccion", "electrico", "electrico-bombilla-casquillo", "electrico-conector", "electrico-interruptor-rele", "encendido", "escapes-emisiones", "freno-maza-rueda", "interior", "limpiaparabrisas", "motor", "rueda", "sistema-enfriamiento", "suspension", "transmision-automatica", "transmision-manual", "tren-transmision"],
      "activa": true,
      "popular": true
    },
    {
      "id": "q60",
      "nombre": "Q60",
      "slug": "q60",
      "años": [2017, 2018, 2019, 2020, 2021, 2022, 2023, 2024],
      "generaciones": [
        {
          "nombre": "Primera Generación (2017-presente)",
          "años": [2017, 2018, 2019, 2020, 2021, 2022, 2023, 2024],
          "caracteristicas": ["Motor 2.0L Turbo/3.0L V6 Turbo", "Transmisión automática 7 velocidades", "Tracción trasera/AWD", "Coupé deportivo de lujo"]
        }
      ],
      "categorias": ["calefaccion-aire-acondicionado", "carroceria-ensamblaje-lampara", "combustible-aire", "correa-transmision", "direccion", "electrico", "electrico-bombilla-casquillo", "electrico-conector", "electrico-interruptor-rele", "encendido", "escapes-emisiones", "freno-maza-rueda", "interior", "limpiaparabrisas", "motor", "rueda", "sistema-enfriamiento", "suspension", "transmision-automatica", "transmision-manual", "tren-transmision"],
      "activa": true,
      "popular": false
    },
    {
      "id": "qx50",
      "nombre": "QX50",
      "slug": "qx50",
      "años": [2013, 2014, 2015, 2016, 2017, 2018, 2019, 2020, 2021, 2022, 2023, 2024],
      "generaciones": [
        {
          "nombre": "Primera Generación (2013-2017)",
          "años": [2013, 2014, 2015, 2016, 2017],
          "caracteristicas": ["Motor 3.7L V6", "Transmisión automática 7 velocidades", "Tracción trasera/AWD", "SUV compacto de lujo"]
        },
        {
          "nombre": "Segunda Generación (2018-presente)",
          "años": [2018, 2019, 2020, 2021, 2022, 2023, 2024],
          "caracteristicas": ["Motor 2.0L Turbo VC", "Transmisión CVT", "Tracción delantera/AWD", "SUV compacto de lujo"]
        }
      ],
      "categorias": ["calefaccion-aire-acondicionado", "carroceria-ensamblaje-lampara", "combustible-aire", "correa-transmision", "direccion", "electrico", "electrico-bombilla-casquillo", "electrico-conector", "electrico-interruptor-rele", "encendido", "escapes-emisiones", "freno-maza-rueda", "interior", "limpiaparabrisas", "motor", "rueda", "sistema-enfriamiento", "suspension", "transmision-automatica", "transmision-manual", "tren-transmision"],
      "activa": true,
      "popular": true
    },
    {
      "id": "qx60",
      "nombre": "QX60",
      "slug": "qx60",
      "años": [2013, 2014, 2015, 2016, 2017, 2018, 2019, 2020, 2021, 2022, 2023, 2024],
      "generaciones": [
        {
          "nombre": "Primera Generación (2013-2021)",
          "años": [2013, 2014, 2015, 2016, 2017, 2018, 2019, 2020, 2021],
          "caracteristicas": ["Motor 3.5L V6", "Transmisión CVT", "Tracción delantera/AWD", "SUV mediano de lujo"]
        },
        {
          "nombre": "Segunda Generación (2022-presente)",
          "años": [2022, 2023, 2024],
          "caracteristicas": ["Motor 3.5L V6", "Transmisión automática 9 velocidades", "Tracción delantera/AWD", "SUV mediano de lujo"]
        }
      ],
      "categorias": ["calefaccion-aire-acondicionado", "carroceria-ensamblaje-lampara", "combustible-aire", "correa-transmision", "direccion", "electrico", "electrico-bombilla-casquillo", "electrico-conector", "electrico-interruptor-rele", "encendido", "escapes-emisiones", "freno-maza-rueda", "interior", "limpiaparabrisas", "motor", "rueda", "sistema-enfriamiento", "suspension", "transmision-automatica", "transmision-manual", "tren-transmision"],
      "activa": true,
      "popular": false
    },
    {
      "id": "qx70",
      "nombre": "QX70",
      "slug": "qx70",
      "años": [2014, 2015, 2016, 2017],
      "generaciones": [
        {
          "nombre": "Primera Generación (2014-2017)",
          "años": [2014, 2015, 2016, 2017],
          "caracteristicas": ["Motor 3.7L V6/5.0L V8", "Transmisión automática 7 velocidades", "Tracción trasera/AWD", "SUV deportivo de lujo"]
        }
      ],
      "categorias": ["calefaccion-aire-acondicionado", "carroceria-ensamblaje-lampara", "combustible-aire", "correa-transmision", "direccion", "electrico", "electrico-bombilla-casquillo", "electrico-conector", "electrico-interruptor-rele", "encendido", "escapes-emisiones", "freno-maza-rueda", "interior", "limpiaparabrisas", "motor", "rueda", "sistema-enfriamiento", "suspension", "transmision-automatica", "transmision-manual", "tren-transmision"],
      "activa": true,
      "popular": false
    },
    {
      "id": "qx80",
      "nombre": "QX80",
      "slug": "qx80",
      "años": [2014, 2015, 2016, 2017, 2018, 2019, 2020, 2021, 2022, 2023, 2024],
      "generaciones": [
        {
          "nombre": "Primera Generación (2014-presente)",
          "años": [2014, 2015, 2016, 2017, 2018, 2019, 2020, 2021, 2022, 2023, 2024],
          "caracteristicas": ["Motor 5.6L V8", "Transmisión automática 7 velocidades", "Tracción trasera/AWD", "SUV full-size de lujo"]
        }
      ],
      "categorias": ["calefaccion-aire-acondicionado", "carroceria-ensamblaje-lampara", "combustible-aire", "correa-transmision", "direccion", "electrico", "electrico-bombilla-casquillo", "electrico-conector", "electrico-interruptor-rele", "encendido", "escapes-emisiones", "freno-maza-rueda", "interior", "limpiaparabrisas", "motor", "rueda", "sistema-enfriamiento", "suspension", "transmision-automatica", "transmision-manual", "tren-transmision"],
      "activa": true,
      "popular": false
    },
    {
      "id": "g37",
      "nombre": "G37",
      "slug": "g37",
      "años": [2008, 2009, 2010, 2011, 2012, 2013],
      "generaciones": [
        {
          "nombre": "Primera Generación (2008-2013)",
          "años": [2008, 2009, 2010, 2011, 2012, 2013],
          "caracteristicas": ["Motor 3.7L V6", "Transmisión manual/automática 6-7 velocidades", "Tracción trasera/AWD", "Sedán/Coupé deportivo de lujo"]
        }
      ],
      "categorias": ["calefaccion-aire-acondicionado", "carroceria-ensamblaje-lampara", "combustible-aire", "correa-transmision", "direccion", "electrico", "electrico-bombilla-casquillo", "electrico-conector", "electrico-interruptor-rele", "encendido", "escapes-emisiones", "freno-maza-rueda", "interior", "limpiaparabrisas", "motor", "rueda", "sistema-enfriamiento", "suspension", "transmision-automatica", "transmision-manual", "tren-transmision"],
      "activa": true,
      "popular": false
    }
  ]
}